hypy/__init__.py
hypy/__main__.py
hypy/cli_main.py
hypy/cli_snap.py
hypy/cli_switch.py
hypy/hypy.conf.example
hypy/modules/__init__.py
hypy/modules/cache.py
hypy/modules/config.py
hypy/modules/hvclient.py
hypy/modules/printer.py
hypy/modules/snaptree.py
hypy3-0.3.6.dist-info/entry_points.txt
hypy3-0.3.6.dist-info/LICENSE
hypy3-0.3.6.dist-info/WHEEL
hypy3-0.3.6.dist-info/METADATA
hypy3-0.3.6.dist-info/RECORD
